stix_shifter_modules/stix_bundle/__init__.py
stix_shifter_modules/stix_bundle/entry_point.py
stix_shifter_modules/stix_bundle/configuration/config.json
stix_shifter_modules/stix_bundle/configuration/dialects.json
stix_shifter_modules/stix_bundle/configuration/lang_en.json
stix_shifter_modules/stix_bundle/stix_translation/__init__.py
stix_shifter_modules/stix_bundle/stix_translation/json_to_stix_translator.py
stix_shifter_modules/stix_bundle/stix_translation/query_translator.py
stix_shifter_modules/stix_bundle/stix_translation/results_translator.py
stix_shifter_modules/stix_bundle/stix_transmission/__init__.py
stix_shifter_modules/stix_bundle/stix_transmission/connector.py
stix_shifter_modules/stix_bundle/test/qradar_observed_2000.json
stix_shifter_modules_stix_bundle-8.0.2.dist-info/licenses/AUTHORS.md
stix_shifter_modules_stix_bundle-8.0.2.dist-info/licenses/LICENSE.md
stix_shifter_modules_stix_bundle-8.0.2.dist-info/licenses/NOTICE
stix_shifter_modules_stix_bundle-8.0.2.dist-info/METADATA
stix_shifter_modules_stix_bundle-8.0.2.dist-info/WHEEL
stix_shifter_modules_stix_bundle-8.0.2.dist-info/top_level.txt
stix_shifter_modules_stix_bundle-8.0.2.dist-info/RECORD
